tcom/__init__.py
tcom/catalog.py
tcom/component.py
tcom/exceptions.py
tcom/html_attrs.py
tcom/jinjax.py
tcom/middleware.py
tcom/py.typed
tcom/utils.py
tcom-0.16.dist-info/WHEEL
tcom-0.16.dist-info/METADATA
tcom-0.16.dist-info/RECORD
